solar/__init__.py
solar/api/__init__.py
solar/api/base.py
solar/api/export.py
solar/api/import_.py
solar/cli.py
solar/cmd/__init__.py
solar/cmd/export.py
solar/cmd/import_.py
solar/config.py
solar/types/__init__.py
solar/types/analysis.py
solar/types/base.py
solar/types/cluster_status.py
solar/types/config_files.py
solar/utils.py
solar_cli-1.0.0.dist-info/entry_points.txt
solar_cli-1.0.0.dist-info/METADATA
solar_cli-1.0.0.dist-info/WHEEL
solar_cli-1.0.0.dist-info/RECORD
