Metadata-Version: 2.1
Name: solar-cli
Version: 1.0.0
Summary: CLI app for Solr
License: MIT
Author: Andrey S.
Author-email: andrewsapw@gmail.com
Requires-Python: >=3.8,<4.0
Classifier: License :: OSI Approved :: MIT License
Classifier: Programming Language :: Python :: 3
Classifier: Programming Language :: Python :: 3.8
Classifier: Programming Language :: Python :: 3.9
Classifier: Programming Language :: Python :: 3.10
Classifier: Programming Language :: Python :: 3.11
Requires-Dist: aiohttp (>=3.8.4,<4.0.0)
Requires-Dist: click (>=8.1.3,<9.0.0)
Requires-Dist: more-itertools (>=9.1.0,<10.0.0)
Requires-Dist: orjson (>=3.8.7,<4.0.0)
Requires-Dist: pydantic (>=1.10.6,<2.0.0)
Requires-Dist: rich (>=13.3.2,<14.0.0)
